conf.py
flexlate_dev/__init__.py
flexlate_dev/cli.py
flexlate_dev/cli_validators.py
flexlate_dev/command_runner.py
flexlate_dev/config.py
flexlate_dev/config_schema.py
flexlate_dev/dict_merge.py
flexlate_dev/dirutils.py
flexlate_dev/exc.py
flexlate_dev/ext_flexlate.py
flexlate_dev/ext_subprocess.py
flexlate_dev/ext_threading.py
flexlate_dev/external_command_type.py
flexlate_dev/get_version.py
flexlate_dev/gitutils.py
flexlate_dev/ignore.py
flexlate_dev/logger.py
flexlate_dev/project_ops.py
flexlate_dev/publish.py
flexlate_dev/render.py
flexlate_dev/server/__init__.py
flexlate_dev/server/back_sync.py
flexlate_dev/server/main.py
flexlate_dev/server/sync.py
flexlate_dev/styles.py
flexlate_dev/user_command.py
flexlate_dev/user_runner.py
version.py
flexlate_dev-0.22.0.dist-info/METADATA
flexlate_dev-0.22.0.dist-info/entry_points.txt
flexlate_dev-0.22.0.dist-info/WHEEL
flexlate_dev-0.22.0.dist-info/LICENSE.md
flexlate_dev-0.22.0.dist-info/RECORD
