Metadata-Version: 2.1
Name: flexlate-dev
Version: 0.22.0
Summary: Development tools for template authors using Flexlate
License: MIT
Author: Nick DeRobertis
Author-email: derobertis.nick@gmail.com
Requires-Python: >=3.8,<4.0
Classifier: Development Status :: 3 - Alpha
Classifier: Intended Audience :: Developers
Classifier: License :: OSI Approved :: MIT License
Classifier: Programming Language :: Python :: 3
Classifier: Programming Language :: Python :: 3.8
Classifier: Programming Language :: Python :: 3.9
Classifier: Programming Language :: Python :: 3.10
Classifier: Programming Language :: Python :: 3.11
Classifier: Programming Language :: Python :: 3.10
Classifier: Programming Language :: Python :: 3.11
Classifier: Programming Language :: Python :: 3.7
Classifier: Programming Language :: Python :: 3.8
Classifier: Programming Language :: Python :: 3.9
Requires-Dist: flexlate (>=0.14.7)
Requires-Dist: patch
Requires-Dist: py-app-conf (>=1.1.0)
Requires-Dist: rich
Requires-Dist: typer
Requires-Dist: unidiff
Requires-Dist: watchdog
Project-URL: documentation, https://nickderobertis.github.io/flexlate-dev
Project-URL: repository, https://github.com/nickderobertis/flexlate-dev
